networkdoctor/__init__.py
networkdoctor/main.py
networkdoctor/server.py
networkdoctor/cli/__init__.py
networkdoctor/cli/help_generator.py
networkdoctor/cli/interactive_menu.py
networkdoctor/cli/parser.py
networkdoctor/cli/progress.py
networkdoctor/cli/validator.py
networkdoctor/core/__init__.py
networkdoctor/core/analyzer.py
networkdoctor/core/doctor.py
networkdoctor/core/intelligence.py
networkdoctor/core/scanner.py
networkdoctor/data/__init__.py
networkdoctor/data/patterns.json
networkdoctor/data/ports.json
networkdoctor/data/solutions.json
networkdoctor/data/vendors.json
networkdoctor/global/__init__.py
networkdoctor/global/global_monitor.py
networkdoctor/global/threat_intelligence.py
networkdoctor/integrations/__init__.py
networkdoctor/integrations/api_server.py
networkdoctor/integrations/email_reporter.py
networkdoctor/integrations/prometheus_exporter.py
networkdoctor/integrations/slack_notifier.py
networkdoctor/integrations/webhook_sender.py
networkdoctor/intelligence/__init__.py
networkdoctor/intelligence/correlation_engine.py
networkdoctor/intelligence/knowledge_base.py
networkdoctor/intelligence/ml_predictor.py
networkdoctor/intelligence/rule_engine.py
networkdoctor/modules/__init__.py
networkdoctor/modules/ai_root_cause.py
networkdoctor/modules/application_layer_doctor.py
networkdoctor/modules/auto_network_repair.py
networkdoctor/modules/cable_fiber_analyst.py
networkdoctor/modules/cloud_network_doctor.py
networkdoctor/modules/dns_doctor.py
networkdoctor/modules/enterprise_network_doctor.py
networkdoctor/modules/firewall_detector.py
networkdoctor/modules/internet_quality_score.py
networkdoctor/modules/iot_network_checker.py
networkdoctor/modules/isp_throttle_detector.py
networkdoctor/modules/network_capacity_planner.py
networkdoctor/modules/offline_diagnosis.py
networkdoctor/modules/performance_analyst.py
networkdoctor/modules/predictive_failure.py
networkdoctor/modules/protocol_analyst.py
networkdoctor/modules/routing_expert.py
networkdoctor-3.0.0.dist-info/licenses/LICENSE
networkdoctor-3.0.0.dist-info/METADATA
networkdoctor-3.0.0.dist-info/WHEEL
networkdoctor-3.0.0.dist-info/entry_points.txt
networkdoctor-3.0.0.dist-info/top_level.txt
networkdoctor-3.0.0.dist-info/RECORD
