Metadata-Version: 2.4
Name: networkdoctor
Version: 3.0.0
Summary: Ultimate AI-Powered Network Diagnostic Tool
Home-page: https://github.com/frankvena25/NetworkDoctor
Author: frankvena25
Author-email: frankvenas25@gmail.com
Maintainer: frankvena25
Maintainer-email: frankvenas25@gmail.com
License: MIT
Project-URL: Homepage, https://github.com/frankvena25/NetworkDoctor
Project-URL: Documentation, https://github.com/frankvena25/NetworkDoctor/blob/main/README.md
Project-URL: Repository, https://github.com/frankvena25/NetworkDoctor
Project-URL: Issues, https://github.com/frankvena25/NetworkDoctor/issues
Project-URL: Bug Tracker, https://github.com/frankvena25/NetworkDoctor/issues
Keywords: network,diagnostic,troubleshooting,ai,network-analysis,network-monitoring,dns,ssl,security,performance,network-health
Classifier: Development Status :: 4 - Beta
Classifier: Intended Audience :: System Administrators
Classifier: Intended Audience :: Developers
Classifier: Topic :: System :: Networking
Classifier: Topic :: System :: Networking :: Monitoring
Classifier: Topic :: Internet
Classifier: Topic :: Security
Classifier: Programming Language :: Python :: 3
Classifier: Programming Language :: Python :: 3.8
Classifier: Programming Language :: Python :: 3.9
Classifier: Programming Language :: Python :: 3.10
Classifier: Programming Language :: Python :: 3.11
Classifier: Programming Language :: Python :: 3.12
Classifier: License :: OSI Approved :: MIT License
Classifier: Operating System :: OS Independent
Requires-Python: >=3.8
License-File: LICENSE
Requires-Dist: rich>=13.0.0
Requires-Dist: aiohttp>=3.9.0
Requires-Dist: dnspython>=2.4.0
Requires-Dist: psutil>=5.9.0
Requires-Dist: pyyaml>=6.0
Requires-Dist: python-dateutil>=2.8.2
Requires-Dist: colorama>=0.4.6
Requires-Dist: tabulate>=0.9.0
Requires-Dist: ping3>=4.0.0
Requires-Dist: pyOpenSSL>=23.2.0
Provides-Extra: dev
Requires-Dist: pytest>=7.0.0; extra == "dev"
Requires-Dist: pytest-cov>=4.0.0; extra == "dev"
Requires-Dist: black>=23.0.0; extra == "dev"
Requires-Dist: flake8>=6.0.0; extra == "dev"
Requires-Dist: mypy>=1.0.0; extra == "dev"
Dynamic: author-email
Dynamic: home-page
Dynamic: license-file
Dynamic: maintainer-email
Dynamic: requires-python
